[
    {
        "ranking": "1",
        "title": "무화커피",
        "image_url": "https://search.pstatic.net/common?src=https%3A%2F%2Fldb-phinf.pstatic.net%2F20200910_61%2F1599720895720loSlI_JPEG%2FnDPRPe_WSbQ2088DZDtgIXrp.jpg&type=f210_210_domesearch",
        "link": "https://map.naver.com/v5/entry/place/1307155544"
    },
    {
        "ranking": "2",
        "title": "라부아뜨엘",
        "image_url": "https://search.pstatic.net/common?src=https%3A%2F%2Fldb-phinf.pstatic.net%2F20211229_151%2F16407387875732gOU9_JPEG%2FKakaoTalk_20211229_094104106_19.jpg&type=f210_210_domesearch",
        "link": "https://map.naver.com/v5/entry/place/1543801447"
    },
    {
        "ranking": "3",
        "title": "라파테",
        "image_url": "https://search.pstatic.net/common?src=https%3A%2F%2Fldb-phinf.pstatic.net%2F20240312_267%2F1710213840718y2cHo_JPEG%2FIMG_8776.jpeg&type=f210_210_domesearch",
        "link": "https://map.naver.com/v5/entry/place/1836746276"
    },
    {
        "ranking": "4",
        "title": "아우어베이커리 수성못점",
        "image_url": "https://search.pstatic.net/common?src=https%3A%2F%2Fldb-phinf.pstatic.net%2F20240109_289%2F1704791901605xDVAP_JPEG%2F%25C1%25A6%25B8%25F1-%25BE%25F8%25C0%25BD-1.jpg&type=f210_210_domesearch",
        "link": "https://map.naver.com/v5/entry/place/1361522853"
    },
    {
        "ranking": "5",
        "title": "아이니테마파크",
        "image_url": "https://search.pstatic.net/common?src=https%3A%2F%2Fldb-phinf.pstatic.net%2F20230228_31%2F1677570193553z6wyw_JPEG%2F%25BE%25C6%25C0%25CC%25B4%25CF.jpg&type=f210_210_domesearch",
        "link": "https://map.naver.com/v5/entry/place/659913225"
    },
    {
        "ranking": "6",
        "title": "국립대구박물관",
        "image_url": "https://search.pstatic.net/common?src=https%3A%2F%2Fldb-phinf.pstatic.net%2F20211102_273%2F1635826577773Cot6U_JPEG%2FhHr_d37MrflJuBLU0WcA3eoI.jpg&type=f210_210_domesearch",
        "link": "https://map.naver.com/v5/entry/place/11620560"
    },
    {
        "ranking": "7",
        "title": "대구미술관",
        "image_url": "https://search.pstatic.net/common?src=https%3A%2F%2Fldb-phinf.pstatic.net%2F20240409_263%2F1712640672901ee3Gd_JPEG%2F%25C8%25B8%25C8%25AD%25C0%25FB.jpg&type=f210_210_domesearch",
        "link": "https://map.naver.com/v5/entry/place/36667448"
    },
    {
        "ranking": "8",
        "title": "바파바로",
        "image_url": "https://search.pstatic.net/common?src=https%3A%2F%2Fldb-phinf.pstatic.net%2F20240502_147%2F17146604323353h96v_JPEG%2FIMG_5516.jpeg&type=f210_210_domesearch",
        "link": "https://map.naver.com/v5/entry/place/1964462990"
    },
    {
        "ranking": "9",
        "title": "아르떼 수성랜드",
        "image_url": "https://search.pstatic.net/common?src=https%3A%2F%2Fldb-phinf.pstatic.net%2F20210320_6%2F1616199321615N1ih0_JPEG%2FCj3wL-zNTnOM6oK6ewbOiMfX.jpg&type=f210_210_domesearch",
        "link": "https://map.naver.com/v5/entry/place/13072214"
    },
    {
        "ranking": "10",
        "title": "목련양과",
        "image_url": "https://search.pstatic.net/common?src=https%3A%2F%2Fldb-phinf.pstatic.net%2F20240521_227%2F1716296520140tU28w_JPEG%2F_MG_5345.jpeg&type=f210_210_domesearch",
        "link": "https://map.naver.com/v5/entry/place/1960207187"
    },
    {
        "ranking": "11",
        "title": "포켓",
        "image_url": "https://search.pstatic.net/common?src=https%3A%2F%2Fldb-phinf.pstatic.net%2F20200126_153%2F1580036750306xgGo0_JPEG%2FUcC17iwYtczentm3ih0Rszhn.jpeg.jpg&type=f210_210_domesearch",
        "link": "https://map.naver.com/v5/entry/place/1225464723"
    },
    {
        "ranking": "12",
        "title": "수성못",
        "image_url": "https://search.pstatic.net/common?src=https%3A%2F%2Fldb-phinf.pstatic.net%2F20150901_128%2F1441042365303fo3p5_JPEG%2F116678508551620_0.jpg&type=f210_210_domesearch",
        "link": "https://map.naver.com/v5/entry/place/13470879"
    },
    {
        "ranking": "13",
        "title": "스완네",
        "image_url": "https://search.pstatic.net/common?src=https%3A%2F%2Fldb-phinf.pstatic.net%2F20220802_101%2F1659410390070KtoQo_JPEG%2F2.jpg&type=f210_210_domesearch",
        "link": "https://map.naver.com/v5/entry/place/1173392363"
    },
    {
        "ranking": "14",
        "title": "룰리커피 고모점",
        "image_url": "https://search.pstatic.net/common?src=https%3A%2F%2Fldb-phinf.pstatic.net%2F20230118_121%2F1674036687023i3VVB_PNG%2F%25B7%25EA%25B8%25AE%25C4%25BF%25C7%25C7_%25B8%25C5%25C0%25E5_%25B9%25E8%25B0%25E6.png&type=f210_210_domesearch",
        "link": "https://map.naver.com/v5/entry/place/1018724541"
    },
    {
        "ranking": "15",
        "title": "수성못상화동산",
        "image_url": "https://search.pstatic.net/common?src=http%3A%2F%2Fblogfiles.naver.net%2FMjAyNDA0MThfMjQ1%2FMDAxNzEzNDI1Mzg4MzM3.QH3N6bCYJLIQNO4lgN91kOYQI-A4ArGekUtzdhTZEIIg.VN4lPJX2ppluFCB2gXzy9svPpBB2pJqEldWl2rU4g-gg.PNG%2F%25C1%25F6%25B1%25B8%25C0%25C7%25B3%25AF.png%23500x500&type=f210_210_domesearch",
        "link": "https://map.naver.com/v5/entry/place/36610484"
    },
    {
        "ranking": "16",
        "title": "데우스커피",
        "image_url": "https://search.pstatic.net/common?src=https%3A%2F%2Fldb-phinf.pstatic.net%2F20181015_288%2F1539593051823IUwfw_JPEG%2FS6ZqSCKQMeHlOcAKSg4L8hRO.jpeg.jpg&type=f210_210_domesearch",
        "link": "https://map.naver.com/v5/entry/place/1827924325"
    },
    {
        "ranking": "17",
        "title": "수성유원지",
        "image_url": "https://search.pstatic.net/common?src=https%3A%2F%2Fldb-phinf.pstatic.net%2F20150901_84%2F1441042372808la6NK_JPEG%2F116678508867079_0.jpg&type=f210_210_domesearch",
        "link": "https://map.naver.com/v5/entry/place/13470887"
    },
    {
        "ranking": "18",
        "title": "수성패밀리파크",
        "image_url": "https://search.pstatic.net/common?src=http%3A%2F%2Fblogfiles.naver.net%2FMjAyNDAyMTNfNCAg%2FMDAxNzA3ODAzOTIwOTE3.kHD8kvRL7IKTSCH5_o-1X_Q6ouMxg1wYgIiuNngyHckg.qg9M6XNuf8lIRoGAwTLnj03w5MbUEnRI5j9Pt2Qxg5wg.PNG.jung63288%2FIMG%25A3%25DF1707532633896.png%23900x1200&type=f210_210_domesearch",
        "link": "https://map.naver.com/v5/entry/place/19838422"
    },
    {
        "ranking": "19",
        "title": "씨티씨커피 범어점",
        "image_url": "https://search.pstatic.net/common?src=https%3A%2F%2Fldb-phinf.pstatic.net%2F20240215_216%2F1707998773853H8X0t_JPEG%2F941E968D-A6AB-423F-A101-0881E2945D36.jpeg&type=f210_210_domesearch",
        "link": "https://map.naver.com/v5/entry/place/1252706235"
    },
    {
        "ranking": "20",
        "title": "팜다원",
        "image_url": "https://search.pstatic.net/common?src=https%3A%2F%2Fldb-phinf.pstatic.net%2F20210702_33%2F1625210425662y4Ozh_JPEG%2Fz2YseyQLtEfmtkUWIIfWyJFE.jpg&type=f210_210_domesearch",
        "link": "https://map.naver.com/v5/entry/place/1776426299"
    }
]