[
    {
        "ranking": "1",
        "title": "고운사",
        "image_url": "https://search.pstatic.net/common?src=https%3A%2F%2Fldb-phinf.pstatic.net%2F20150831_168%2F1441013644549gfLVo_JPEG%2F106670593456926_0.jpg&type=f210_210_domesearch",
        "link": "11663995",
        "title_cate": "절,사찰",
        "human_review": "",
        "blog_review": "715",
        "addresses": "경북 의성군 고운사길 415"
    },
    {
        "ranking": "2",
        "title": "빙계얼음골 야영장",
        "image_url": "https://search.pstatic.net/common?src=https%3A%2F%2Fldb-phinf.pstatic.net%2F20210811_185%2F1628663608242ULuWc_JPEG%2FcA_EbgYVsCokb14Ftjwc4WxS.jpg&type=f210_210_domesearch",
        "link": "1347086762",
        "title_cate": "캠핑,야영장",
        "human_review": "102",
        "blog_review": "261",
        "addresses": "경북 의성군 가음면 빙계계곡길 51"
    },
    {
        "ranking": "3",
        "title": "빙계계곡",
        "image_url": "https://search.pstatic.net/common?src=https%3A%2F%2Fldb-phinf.pstatic.net%2F20150901_5%2F1441045593428QCH7i_JPEG%2F13491255_0.jpg&type=f210_210_domesearch",
        "link": "13491255",
        "title_cate": "계곡",
        "human_review": "37",
        "blog_review": "263",
        "addresses": "경북 의성군 춘산면 빙계리 896"
    },
    {
        "ranking": "4",
        "title": "금봉자연휴양림",
        "image_url": "https://search.pstatic.net/common?src=https%3A%2F%2Fldb-phinf.pstatic.net%2F20150206_63%2F1423208618096t6AhD_JPEG%2F%25B0%25E6%25BA%25CF_%25C0%25C7%25BC%25BA%25B1%25DD%25BA%25C0%25C0%25DA%25BF%25AC%25C8%25DE%25BE%25E7%25B8%25B2_1.JPG%3Ftype%3Dm500_500&type=f210_210_domesearch",
        "link": "13163539",
        "title_cate": "휴양림,산림욕장",
        "human_review": "12",
        "blog_review": "90",
        "addresses": "경북 의성군 옥산면 금봉리 산24-1"
    },
    {
        "ranking": "5",
        "title": "의성조문국박물관",
        "image_url": "https://search.pstatic.net/common?src=http%3A%2F%2Fblogfiles.naver.net%2FMjAxODAxMDhfMTky%2FMDAxNTE1NDIyNjM5MjI0.1neFe2uNPq0Y7rgLDrwsl1cctdb8AslWDh3hhK7ekO8g.Y3R0T59Y-PSt0cw9VOnrIfSLR6gE1RlFUHW1zOr65ZQg.JPEG.hongga4%2FP1140850.JPG%233232x1824&type=f210_210_domesearch",
        "link": "32514292",
        "title_cate": "박물관",
        "human_review": "621",
        "blog_review": "707",
        "addresses": "경북 의성군 금성면 초전1길 83"
    },
    {
        "ranking": "6",
        "title": "사촌전통마을",
        "image_url": "https://search.pstatic.net/common?src=http%3A%2F%2Fblogfiles.naver.net%2FMjAxNzExMDNfMjYg%2FMDAxNTA5Njg0Mjg2NzI1.wS9XD1oLV9lghP7cnejMG_QO4H3RFrzWfjhzNMXh7Egg.8aceqcPeTgYaOn_25pXFB-BWit9piFpyCkIQ1vFAAHIg.JPEG.han4869%2FDSC03586.jpg%23900x600&type=f210_210_domesearch",
        "link": "20061798",
        "title_cate": "체험마을",
        "human_review": "6",
        "blog_review": "162",
        "addresses": "경북 의성군 만취당길 69"
    },
    {
        "ranking": "7",
        "title": "구계밀리",
        "image_url": "https://search.pstatic.net/common?src=https%3A%2F%2Fldb-phinf.pstatic.net%2F20240306_112%2F1709689612698FHfNO_JPEG%2F%25B1%25B8%25B0%25E8%25B9%25D0%25B8%25AE_%25B7%25CE%25B0%25ED.jpg&type=f210_210_domesearch",
        "link": "1719689247",
        "title_cate": "카페,디저트",
        "human_review": "5",
        "blog_review": "40",
        "addresses": "경북 의성군 단촌면 고운사길 117"
    },
    {
        "ranking": "8",
        "title": "경덕왕릉의성조문국사적지",
        "image_url": "https://search.pstatic.net/common?src=http%3A%2F%2Fblogfiles.naver.net%2FMjAxNzA1MjNfMTUx%2FMDAxNDk1NTA1NTUyMDY1.xYMl2K_l_RtUV4X9jiyoDf-QV-1WASk0omn6a6HNDu8g.KmhBOBnhFJHvpMDYYCbce8OLCM7DjMGIp1envyot-g4g.JPEG.adelheim5811%2FIMG_7254.JPG%232699x1798&type=f210_210_domesearch",
        "link": "705367453",
        "title_cate": "문화,유적",
        "human_review": "8",
        "blog_review": "345",
        "addresses": "경북 의성군 금성면 대리리 324"
    },
    {
        "ranking": "9",
        "title": "구봉공원",
        "image_url": "https://search.pstatic.net/common?src=http%3A%2F%2Fblogfiles.naver.net%2FMjAyNDA1MDNfMjQ4%2FMDAxNzE0NzIzNjA2NDIy.ow-aQWNY87NposmaRi5sXDRvpVhc7afQ2AVwE09l_KYg.i4FlwzGsDsrm0ytruD4tdiEzrF1mDgx3C2CSVYHbiycg.PNG%2F0503.png%23500x500&type=f210_210_domesearch",
        "link": "15890641",
        "title_cate": "근린공원",
        "human_review": "27",
        "blog_review": "105",
        "addresses": "경북 의성군 의성읍 도서리 286"
    },
    {
        "ranking": "10",
        "title": "MODERN29",
        "image_url": "https://search.pstatic.net/common?src=https%3A%2F%2Fldb-phinf.pstatic.net%2F20190702_271%2F1561997690190GaOW1_JPEG%2Ft5MRk_ctAals8fILl5JBl8FU.jpeg.jpg&type=f210_210_domesearch",
        "link": "1625219338",
        "title_cate": "카페,디저트",
        "human_review": "671",
        "blog_review": "37",
        "addresses": "경북 의성군 봉양면 도리원3길 29-1 모던29카페"
    },
    {
        "ranking": "11",
        "title": "스윗띵",
        "image_url": "https://search.pstatic.net/common?src=https%3A%2F%2Fldb-phinf.pstatic.net%2F20220313_204%2F1647181936898KqCDx_JPEG%2F8F29666D-248A-4CF8-BE04-A0752C4D1F82.jpeg&type=f210_210_domesearch",
        "link": "1773638114",
        "title_cate": "카페,디저트",
        "human_review": "105",
        "blog_review": "58",
        "addresses": "경북 의성군 안계면 용기12길 23 1층"
    },
    {
        "ranking": "12",
        "title": "추추",
        "image_url": "https://search.pstatic.net/common?src=https%3A%2F%2Fldb-phinf.pstatic.net%2F20240117_175%2F1705481450451fX6lc_JPEG%2FIMG_0357.jpeg&type=f210_210_domesearch",
        "link": "1411041917",
        "title_cate": "카페,디저트",
        "human_review": "35",
        "blog_review": "47",
        "addresses": "경북 의성군 금성면 탑리5길 34"
    },
    {
        "ranking": "13",
        "title": "달빛공원",
        "image_url": "https://search.pstatic.net/common?src=http%3A%2F%2Fblogfiles.naver.net%2FMjAyNDA1MjRfMjk3%2FMDAxNzE2NTQwNjgyNjY2.R9rny2DAn4NFIohHmJPODdqf8TZxN0T1_B6aJ71Umqsg.3bQmfrCDbUSeuBQdCLVSSaNCRoSYGZljpEjaFxZjPhYg.PNG%2F2023_%25C0%25C7%25BC%25BA%25B1%25BA_%25BD%25E6%25B3%25D7%25C0%25CF.png%23500x500&type=f210_210_domesearch",
        "link": "33005945",
        "title_cate": "근린공원",
        "human_review": "10",
        "blog_review": "134",
        "addresses": "경북 의성군 사곡면 양지리 산64-2"
    },
    {
        "ranking": "14",
        "title": "의성공설전통시장",
        "image_url": "https://search.pstatic.net/common?src=http%3A%2F%2Fblogfiles.naver.net%2FMjAyMDAxMjJfMjU0%2FMDAxNTc5NjU5MTQ1OTUx.N1OURS8wmXCXGkm9OMWZHd_p_NzITeM7I5ryyBWiwrsg.E_ythQ0hYy39K9XdygNJtvkMTPES9qpHDXvi_fxFOuog.JPEG.ojhloo4%2F1579659137536.jpg%234032x3024&type=f210_210_domesearch",
        "link": "1689822760",
        "title_cate": "시장",
        "human_review": "5",
        "blog_review": "100",
        "addresses": "경북 의성군 전통시장1길 15-3"
    },
    {
        "ranking": "15",
        "title": "오밀조밀",
        "image_url": "https://search.pstatic.net/common?src=https%3A%2F%2Fldb-phinf.pstatic.net%2F20230424_209%2F16823325199709S8Vy_JPEG%2Fart_16280425776128_aa1c07.jpg&type=f210_210_domesearch",
        "link": "1717186985",
        "title_cate": "베이커리",
        "human_review": "75",
        "blog_review": "17",
        "addresses": "경북 의성군 의성읍 동서1길 107"
    },
    {
        "ranking": "16",
        "title": "카페나인",
        "image_url": "https://search.pstatic.net/common?src=https%3A%2F%2Fldb-phinf.pstatic.net%2F20220821_12%2F1661060626557GHmie_JPEG%2FE755A3DA-943D-4F27-BDAD-179274DA577A.jpeg&type=f210_210_domesearch",
        "link": "1252262190",
        "title_cate": "카페,디저트",
        "human_review": "198",
        "blog_review": "48",
        "addresses": "경북 의성군 의성읍 남대천길 170"
    },
    {
        "ranking": "17",
        "title": "고운마을캠핑장",
        "image_url": "https://search.pstatic.net/common?src=https%3A%2F%2Fldb-phinf.pstatic.net%2F20220218_3%2F16451486035009d4wp_JPEG%2F1634472253.jpg&type=f210_210_domesearch",
        "link": "1414538988",
        "title_cate": "캠핑,야영장",
        "human_review": "20",
        "blog_review": "81",
        "addresses": "경북 의성군 단촌면 고운사길 203-21 고운마을캠핑장"
    },
    {
        "ranking": "18",
        "title": "산운생태공원",
        "image_url": "https://search.pstatic.net/common?src=https%3A%2F%2Fldb-phinf.pstatic.net%2F20150901_237%2F14410349989033lTzJ_JPEG%2F126956604540185_0.jpg&type=f210_210_domesearch",
        "link": "20118997",
        "title_cate": "자연,생태공원",
        "human_review": "7",
        "blog_review": "251",
        "addresses": "경북 의성군 금성면 수정사길 19"
    },
    {
        "ranking": "19",
        "title": "카페아리",
        "image_url": "https://search.pstatic.net/common?src=https%3A%2F%2Fldb-phinf.pstatic.net%2F20230926_145%2F16956633409529WCvz_JPEG%2FIMG_9100.jpeg&type=f210_210_domesearch",
        "link": "1803309337",
        "title_cate": "카페,디저트",
        "human_review": "168",
        "blog_review": "36",
        "addresses": "경북 의성군 금성면 산운리 667-9"
    },
    {
        "ranking": "20",
        "title": "금성산",
        "image_url": "https://search.pstatic.net/common?src=https%3A%2F%2Fldb-phinf.pstatic.net%2F20150901_263%2F1441045588254jtq6y_JPEG%2F13491218_0.jpg&type=f210_210_domesearch",
        "link": "13491218",
        "title_cate": "산",
        "human_review": "",
        "blog_review": "76",
        "addresses": "경북 의성군 금성면 탑리리"
    }
]