[
    {
        "ranking": "1",
        "title": "서울시립 북서울미술관",
        "image_url": "https://search.pstatic.net/common?src=https%3A%2F%2Fldb-phinf.pstatic.net%2F20150831_5%2F1440994935211TQqG9_JPEG%2F146979518555954_0.jpeg&type=f210_210_domesearch",
        "link": "18654445",
        "title_cate": "미술관",
        "human_review": "142",
        "blog_review": "4,181",
        "addresses": "서울 노원구 동일로 1238",
        "x": "127.0667885",
        "y": "37.6409659"
    },
    {
        "ranking": "2",
        "title": "서울시립과학관",
        "image_url": "https://search.pstatic.net/common?src=https%3A%2F%2Fldb-phinf.pstatic.net%2F20230721_230%2F1689916742744KaG2v_JPEG%2F%25B0%25FA%25C7%25D0%25B0%25FC_%25C1%25A4%25B8%25E9%25BB%25E7%25C1%25F8_1.JPG&type=f210_210_domesearch",
        "link": "515824798",
        "title_cate": "과학관",
        "human_review": "696",
        "blog_review": "1,104",
        "addresses": "서울 노원구 한글비석로 160 서울시립과학관",
        "x": "127.0776118",
        "y": "37.6419787"
    },
    {
        "ranking": "3",
        "title": "화랑대 철도공원",
        "image_url": "https://search.pstatic.net/common?src=https%3A%2F%2Fldb-phinf.pstatic.net%2F20181022_185%2F1540181553799zMA74_JPEG%2FK5uD-2HkzCa4IOPhNa9cPb-7.jpg&type=f210_210_domesearch",
        "link": "1895218381",
        "title_cate": "도시,테마공원",
        "human_review": "98",
        "blog_review": "2,059",
        "addresses": "서울 노원구 공릉동 29-51",
        "x": "127.0928481",
        "y": "37.6240911"
    },
    {
        "ranking": "4",
        "title": "벽운계곡",
        "image_url": "https://search.pstatic.net/common?src=http%3A%2F%2Fblogfiles.naver.net%2FMjAyMzA4MDVfMTg0%2FMDAxNjkxMjMzOTM2Mzk5.Fkerz5JafaQAjXhfz00oT_-oUq9-SLB5LTg-TuQu6yog.Xces8vEGqEGDO0RJj_VVWSrsxaskgphIKAOV6bOTE2Mg.JPEG.krworker%2F1691233913490.jpg%23900x900&type=f210_210_domesearch",
        "link": "18645990",
        "title_cate": "계곡",
        "human_review": "6",
        "blog_review": "201",
        "addresses": "서울 노원구 상계동",
        "x": "127.0623597",
        "y": "37.6844343"
    },
    {
        "ranking": "5",
        "title": "물레",
        "image_url": "https://search.pstatic.net/common?src=https%3A%2F%2Fldb-phinf.pstatic.net%2F20200611_278%2F1591858707613W0RAq_JPEG%2FE4Lk5dUJJveHkQ19oikk6aZX.jpeg.jpg&type=f210_210_domesearch",
        "link": "1143872310",
        "title_cate": "카페",
        "human_review": "946",
        "blog_review": "595",
        "addresses": "서울 노원구 노해로81길 12-20",
        "x": "127.0640506",
        "y": "37.655593"
    },
    {
        "ranking": "6",
        "title": "불암산",
        "image_url": "https://search.pstatic.net/common?src=https%3A%2F%2Fldb-phinf.pstatic.net%2F20150901_263%2F14410457085394RxGP_JPEG%2F13491957_0.jpg&type=f210_210_domesearch",
        "link": "13491957",
        "title_cate": "산",
        "human_review": "71",
        "blog_review": "3,451",
        "addresses": "서울 노원구 상계동",
        "x": "127.0952714",
        "y": "37.6636718"
    },
    {
        "ranking": "7",
        "title": "서울생활사박물관",
        "image_url": "https://search.pstatic.net/common?src=https%3A%2F%2Fldb-phinf.pstatic.net%2F20240502_31%2F1714614270323nPBn7_JPEG%2F650x975_%25281%2529.jpg&type=f210_210_domesearch",
        "link": "1121351765",
        "title_cate": "박물관",
        "human_review": "83",
        "blog_review": "1,337",
        "addresses": "서울 노원구 동일로174길 27",
        "x": "127.0768892",
        "y": "37.6199447"
    },
    {
        "ranking": "8",
        "title": "중계마을",
        "image_url": "https://search.pstatic.net/common?src=http%3A%2F%2Fblogfiles.naver.net%2FMjAyNDA1MTVfMTk5%2FMDAxNzE1NzI3MTY0NTAy.ozkcJ8IUVQSkTb4zf9JEs_FVqNw9tLgpA0J9ojs_4sEg.ATwGOxgY-sWhZ9bGuh8y8Zov4xBXySYTidaHfEsn_YIg.JPEG%2F20240513_124205.jpg%23800x600&type=f210_210_domesearch",
        "link": "34581407",
        "title_cate": "체험마을",
        "human_review": "68",
        "blog_review": "212",
        "addresses": "서울 노원구 중계본동 104-3",
        "x": "127.0885492",
        "y": "37.6448334"
    },
    {
        "ranking": "9",
        "title": "커피콩",
        "image_url": "https://search.pstatic.net/common?src=https%3A%2F%2Fldb-phinf.pstatic.net%2F20220117_195%2F16423856589390hQxf_JPEG%2F20220103_220616.jpg&type=f210_210_domesearch",
        "link": "31744094",
        "title_cate": "카페",
        "human_review": "559",
        "blog_review": "212",
        "addresses": "서울 노원구 동일로191가길 19 1층 커피콩",
        "x": "127.0711671",
        "y": "37.6259168"
    },
    {
        "ranking": "10",
        "title": "월드킹 노원점",
        "image_url": "https://search.pstatic.net/common?src=https%3A%2F%2Fldb-phinf.pstatic.net%2F20231104_249%2F1699052876944fqGoX_PNG%2FDCOVER_20231104_080702.png&type=f210_210_domesearch",
        "link": "1766459729",
        "title_cate": "키즈카페,실내놀이터",
        "human_review": "3,639",
        "blog_review": "256",
        "addresses": "서울 노원구 동일로180길 14 2층 001호",
        "x": "127.0752937",
        "y": "37.6220758"
    },
    {
        "ranking": "11",
        "title": "메트로폴리스",
        "image_url": "https://search.pstatic.net/common?src=https%3A%2F%2Fldb-phinf.pstatic.net%2F20221231_5%2F167243878246663Ywi_PNG%2FKakaoTalk_20220611_155114707.png&type=f210_210_domesearch",
        "link": "1815424144",
        "title_cate": "베이커리",
        "human_review": "832",
        "blog_review": "1,036",
        "addresses": "서울 노원구 동일로178길 11-9 1층",
        "x": "127.0751307",
        "y": "37.621478"
    },
    {
        "ranking": "12",
        "title": "moodshare",
        "image_url": "https://search.pstatic.net/common?src=https%3A%2F%2Fldb-phinf.pstatic.net%2F20231125_247%2F1700916222124T9vsv_JPEG%2FKakaoTalk_20231125_214244076_01.jpg&type=f210_210_domesearch",
        "link": "1212622367",
        "title_cate": "카페,디저트",
        "human_review": "519",
        "blog_review": "739",
        "addresses": "서울 노원구 공릉로 119-23 더하우스 1층",
        "x": "127.07794",
        "y": "37.6214794"
    },
    {
        "ranking": "13",
        "title": "베베쿠아 베이비스파카페",
        "image_url": "https://search.pstatic.net/common?src=https%3A%2F%2Fldb-phinf.pstatic.net%2F20230706_273%2F1688647266374euKot_JPEG%2FAC8A9456.jpg&type=f210_210_domesearch",
        "link": "1045494427",
        "title_cate": "키즈카페,실내놀이터",
        "human_review": "1,641",
        "blog_review": "246",
        "addresses": "서울 노원구 섬밭로 258 건영백화점 4층",
        "x": "127.0648461",
        "y": "37.6388763"
    },
    {
        "ranking": "14",
        "title": "라라브레드 공릉점",
        "image_url": "https://search.pstatic.net/common?src=https%3A%2F%2Fldb-phinf.pstatic.net%2F20190410_212%2F1554870778439DWFM5_JPEG%2FpkYFd2V-Mi481kN4h5OkFkzW.JPG.jpg&type=f210_210_domesearch",
        "link": "1062761073",
        "title_cate": "베이커리",
        "human_review": "6,054",
        "blog_review": "1,207",
        "addresses": "서울 노원구 공릉로41길 32",
        "x": "127.0778667",
        "y": "37.6248554"
    },
    {
        "ranking": "15",
        "title": "감각",
        "image_url": "https://search.pstatic.net/common?src=https%3A%2F%2Fldb-phinf.pstatic.net%2F20190415_181%2F1555309175080KVYhM_PNG%2FciKhp_T7dIPibA10B4TCl18E.png&type=f210_210_domesearch",
        "link": "1794396162",
        "title_cate": "카페",
        "human_review": "1,127",
        "blog_review": "760",
        "addresses": "서울 노원구 상계로 77",
        "x": "127.0634931",
        "y": "37.65683"
    },
    {
        "ranking": "16",
        "title": "불빛정원",
        "image_url": "https://search.pstatic.net/common?src=http%3A%2F%2Fblogfiles.naver.net%2FMjAyNDA0MTJfMjUz%2FMDAxNzEyODcyNzI5MTU3.Tvh_CuC_PLT_Ocb9qU-vpgvnpu41vkmfTNYVu8_GxH8g.LgCvUtcXZdJ0bkHuVo8hnQN5CW_np862mRbOhqbj3-kg.JPEG%2F1712872529573.jpg%23900x1200&type=f210_210_domesearch",
        "link": "1200984778",
        "title_cate": "자연공원",
        "human_review": "22",
        "blog_review": "595",
        "addresses": "서울 노원구 화랑로 608",
        "x": "127.0930898",
        "y": "37.6244509"
    },
    {
        "ranking": "17",
        "title": "블루마일스커피로스터즈",
        "image_url": "https://search.pstatic.net/common?src=https%3A%2F%2Fldb-phinf.pstatic.net%2F20231123_114%2F1700705011900bDGKL_JPEG%2FKakaoTalk_20231123_105839506_11.jpg&type=f210_210_domesearch",
        "link": "1505598385",
        "title_cate": "카페",
        "human_review": "1,125",
        "blog_review": "569",
        "addresses": "서울 노원구 동일로190길 65 2층",
        "x": "127.0766479",
        "y": "37.6265601"
    },
    {
        "ranking": "18",
        "title": "수락산",
        "image_url": "https://search.pstatic.net/common?src=https%3A%2F%2Fldb-phinf.pstatic.net%2F20150901_41%2F1441045699917QBLVE_JPEG%2F13491904_0.jpg&type=f210_210_domesearch",
        "link": "13491904",
        "title_cate": "산",
        "human_review": "60",
        "blog_review": "3,457",
        "addresses": "서울 노원구 상계동",
        "x": "127.0813633",
        "y": "37.699232"
    },
    {
        "ranking": "19",
        "title": "시드누아 노원본점",
        "image_url": "https://search.pstatic.net/common?src=https%3A%2F%2Fldb-phinf.pstatic.net%2F20190430_119%2F1556596448087f1XXo_JPEG%2FI8TZMwceAzMdyVqwYCt9548O.jpeg.jpg&type=f210_210_domesearch",
        "link": "38019327",
        "title_cate": "카페",
        "human_review": "3,821",
        "blog_review": "791",
        "addresses": "서울 노원구 상계로 84",
        "x": "127.0642411",
        "y": "37.6563524"
    },
    {
        "ranking": "20",
        "title": "키즈런 스포츠파크",
        "image_url": "https://search.pstatic.net/common?src=https%3A%2F%2Fldb-phinf.pstatic.net%2F20230722_240%2F1689991842193XBbv2_JPEG%2F20230617_152519.jpg&type=f210_210_domesearch",
        "link": "1443002577",
        "title_cate": "키즈카페,실내놀이터",
        "human_review": "1,476",
        "blog_review": "241",
        "addresses": "서울 노원구 섬밭로 258 4층",
        "x": "127.0648461",
        "y": "37.6388763"
    }
]