[
    {
        "ranking": "1",
        "title": "서울식물원",
        "image_url": "https://search.pstatic.net/common?src=https%3A%2F%2Fldb-phinf.pstatic.net%2F20221107_278%2F16678003154765lmfT_JPEG%2F%25C0%25FC%25BD%25C3%25BF%25C2%25BD%25C7_%25BE%25DF%25B0%25A3.jpg&type=f210_210_domesearch",
        "link": "1932878505",
        "title_cate": "식물원,수목원",
        "human_review": "8,157",
        "blog_review": "17,846",
        "addresses": "서울 강서구 마곡동로 161 서울식물원"
    },
    {
        "ranking": "2",
        "title": "LG아트센터 서울",
        "image_url": "https://search.pstatic.net/common?src=https%3A%2F%2Fldb-phinf.pstatic.net%2F20220621_125%2F1655784935828QYSV6_JPEG%2F20220621510467.jpg&type=f210_210_domesearch",
        "link": "11576168",
        "title_cate": "공연장",
        "human_review": "559",
        "blog_review": "7,770",
        "addresses": "서울 강서구 마곡중앙로 136 LG아트센터 서울"
    },
    {
        "ranking": "3",
        "title": "베이글리스트",
        "image_url": "https://search.pstatic.net/common?src=https%3A%2F%2Fldb-phinf.pstatic.net%2F20230714_199%2F1689293831272NIviF_JPEG%2Fooj-113-min.JPG&type=f210_210_domesearch",
        "link": "1075532553",
        "title_cate": "베이글",
        "human_review": "1,186",
        "blog_review": "1,479",
        "addresses": "서울 강서구 마곡동로 55 마커스빌딩 102호"
    },
    {
        "ranking": "4",
        "title": "국립항공박물관",
        "image_url": "https://search.pstatic.net/common?src=https%3A%2F%2Fldb-phinf.pstatic.net%2F20201120_257%2F1605854850079eD8Vf_JPEG%2Fcg3nA9RA2gA9A1zjDInCZISY.jpg&type=f210_210_domesearch",
        "link": "983063944",
        "title_cate": "박물관",
        "human_review": "1,246",
        "blog_review": "2,735",
        "addresses": "서울 강서구 하늘길 177"
    },
    {
        "ranking": "5",
        "title": "고드니",
        "image_url": "https://search.pstatic.net/common?src=https%3A%2F%2Fldb-phinf.pstatic.net%2F20240523_85%2F1716442518730zXEBA_JPEG%2FIMG_2324.jpeg&type=f210_210_domesearch",
        "link": "1374736548",
        "title_cate": "카페,디저트",
        "human_review": "789",
        "blog_review": "818",
        "addresses": "서울 강서구 마곡중앙로 161-1 캐슬파크 2층 220, 230호"
    },
    {
        "ranking": "6",
        "title": "어나더사이드",
        "image_url": "https://search.pstatic.net/common?src=https%3A%2F%2Fldb-phinf.pstatic.net%2F20230322_23%2F1679448583997uHhiC_JPEG%2FKakaoTalk_20230322_102204265.jpg&type=f210_210_domesearch",
        "link": "1582128660",
        "title_cate": "카페,디저트",
        "human_review": "3,984",
        "blog_review": "1,837",
        "addresses": "서울 강서구 강서로 318 1층 카페 어나더사이드"
    },
    {
        "ranking": "7",
        "title": "라크루뜨서울 본점",
        "image_url": "https://search.pstatic.net/common?src=https%3A%2F%2Fldb-phinf.pstatic.net%2F20240417_236%2F17133418650187O6Sf_JPEG%2FIMG_6791.JPG&type=f210_210_domesearch",
        "link": "1291332170",
        "title_cate": "베이커리",
        "human_review": "298",
        "blog_review": "490",
        "addresses": "서울 강서구 공항대로 237 111-112호"
    },
    {
        "ranking": "8",
        "title": "베이커리 룬",
        "image_url": "https://search.pstatic.net/common?src=https%3A%2F%2Fldb-phinf.pstatic.net%2F20220928_157%2F1664335633612rXPYa_JPEG%2FEAEC46DC-B1EB-48FB-9FC2-49696D014BD4.jpeg&type=f210_210_domesearch",
        "link": "1018513593",
        "title_cate": "베이커리",
        "human_review": "3,503",
        "blog_review": "595",
        "addresses": "서울 강서구 공항대로 261 발산파크프라자10"
    },
    {
        "ranking": "9",
        "title": "카페 우드진",
        "image_url": "https://search.pstatic.net/common?src=https%3A%2F%2Fldb-phinf.pstatic.net%2F20180725_117%2F1532481430052N5sqD_JPEG%2FSqpxXzPu8LmCY7td8Zqm43fZ.jpg&type=f210_210_domesearch",
        "link": "1745761834",
        "title_cate": "카페,디저트",
        "human_review": "1,374",
        "blog_review": "578",
        "addresses": "서울 강서구 마곡중앙6로 45 카페 우드진"
    },
    {
        "ranking": "10",
        "title": "깅꼬서울",
        "image_url": "https://search.pstatic.net/common?src=https%3A%2F%2Fldb-phinf.pstatic.net%2F20240322_282%2F1711087505769xV7fk_JPEG%2F20240322_112503.jpg&type=f210_210_domesearch",
        "link": "1732725764",
        "title_cate": "카페,디저트",
        "human_review": "278",
        "blog_review": "228",
        "addresses": "서울 강서구 개화10길 40 깅꼬서울"
    },
    {
        "ranking": "11",
        "title": "피코리코 롯데몰 김포공항점",
        "image_url": "https://search.pstatic.net/common?src=https%3A%2F%2Fldb-phinf.pstatic.net%2F20230620_68%2F1687267699575EgQji_JPEG%2FKakaoTalk_20230529_103205581.jpg&type=f210_210_domesearch",
        "link": "1467919063",
        "title_cate": "카페,디저트",
        "human_review": "1,015",
        "blog_review": "397",
        "addresses": "서울 강서구 하늘길 77 롯데몰 김포공항점 GF층"
    },
    {
        "ranking": "12",
        "title": "허준박물관",
        "image_url": "https://search.pstatic.net/common?src=https%3A%2F%2Fldb-phinf.pstatic.net%2F20220118_52%2F16424910816151WXzj_JPEG%2F%25C7%25E3%25C1%25D8%25B9%25DA%25B9%25B0%25B0%25FC%25C0%25FC%25B0%25E6-%25B1%25DB%25C0%25DA-%25B3%25AA%25B9%25AB%25C3%25DF%25B0%25A1.jpg_copy.jpg&type=f210_210_domesearch",
        "link": "11814586",
        "title_cate": "박물관",
        "human_review": "85",
        "blog_review": "1,083",
        "addresses": "서울 강서구 허준로 87 허준박물관"
    },
    {
        "ranking": "13",
        "title": "프레베리 마곡케이크",
        "image_url": "https://search.pstatic.net/common?src=https%3A%2F%2Fldb-phinf.pstatic.net%2F20240501_249%2F1714558001531MChSr_PNG%2F%25BD%25BA%25C5%25A9%25B8%25B0%25BC%25A6_2024-05-01_%25BF%25C0%25C8%25C4_7.06.05.png&type=f210_210_domesearch",
        "link": "1754841765",
        "title_cate": "카페,디저트",
        "human_review": "2,714",
        "blog_review": "724",
        "addresses": "서울 강서구 마곡동로4길 23 1층"
    },
    {
        "ranking": "14",
        "title": "스페이스K 서울",
        "image_url": "https://search.pstatic.net/common?src=https%3A%2F%2Fldb-phinf.pstatic.net%2F20240324_163%2F1711252021564Bo7hp_JPEG%2F2.jpg&type=f210_210_domesearch",
        "link": "1929952881",
        "title_cate": "미술관",
        "human_review": "45",
        "blog_review": "1,276",
        "addresses": "서울 강서구 마곡중앙8로 32 스페이스K 서울"
    },
    {
        "ranking": "15",
        "title": "해례커피 마곡나루역점",
        "image_url": "https://search.pstatic.net/common?src=https%3A%2F%2Fldb-phinf.pstatic.net%2F20231213_79%2F1702399274805EfCw6_JPEG%2FKakaoTalk_20231213_014008923.jpg&type=f210_210_domesearch",
        "link": "1311776578",
        "title_cate": "카페,디저트",
        "human_review": "187",
        "blog_review": "386",
        "addresses": "서울 강서구 마곡중앙로 161-1 캐슬파크 217호"
    },
    {
        "ranking": "16",
        "title": "헤리스헤이스",
        "image_url": "https://search.pstatic.net/common?src=https%3A%2F%2Fldb-phinf.pstatic.net%2F20210529_182%2F16222869809972vSNY_JPEG%2FTNs7jabp-4vk_nAyK9ZPq4Fg.jpeg.jpg&type=f210_210_domesearch",
        "link": "1405015740",
        "title_cate": "카페",
        "human_review": "1,153",
        "blog_review": "555",
        "addresses": "서울 강서구 마곡동로3길 26 103호"
    },
    {
        "ranking": "17",
        "title": "엘리케이커",
        "image_url": "https://search.pstatic.net/common?src=https%3A%2F%2Fldb-phinf.pstatic.net%2F20240315_298%2F1710496273142oheBi_JPEG%2FIMG_7936.jpeg&type=f210_210_domesearch",
        "link": "1643275496",
        "title_cate": "케이크전문",
        "human_review": "430",
        "blog_review": "526",
        "addresses": "서울 강서구 마곡중앙5로 6 보타닉푸르지오시티 동관 G층(혹은 지하1층) B142호"
    },
    {
        "ranking": "18",
        "title": "더 왓에버",
        "image_url": "https://search.pstatic.net/common?src=https%3A%2F%2Fldb-phinf.pstatic.net%2F20220504_151%2F1651595662497PrPy3_JPEG%2F6FE6EC2E-2E3C-46B7-8FD4-BD4550D91F3E.jpeg&type=f210_210_domesearch",
        "link": "1275204644",
        "title_cate": "브런치카페",
        "human_review": "822",
        "blog_review": "630",
        "addresses": "서울 강서구 마곡중앙2로 15"
    },
    {
        "ranking": "19",
        "title": "스위트파크 롯데 어린이 식품체험관",
        "image_url": "https://search.pstatic.net/common?src=https%3A%2F%2Fldb-phinf.pstatic.net%2F20170906_151%2F1504671666715gOj8y_PNG%2FN9qvM7vq3BWNI9sRCKmF1KLp.PNG.png&type=f210_210_domesearch",
        "link": "1637479185",
        "title_cate": "체험,홍보관",
        "human_review": "5",
        "blog_review": "188",
        "addresses": "서울 강서구 마곡중앙로 201 롯데중앙연구소 1층"
    },
    {
        "ranking": "20",
        "title": "KBS아레나",
        "image_url": "https://search.pstatic.net/common?src=https%3A%2F%2Fldb-phinf.pstatic.net%2F20230602_171%2F1685693449497DgkJu_JPEG%2F%25BF%25DC%25BA%25CE_%25C0%25FC%25B0%25E6.jpg&type=f210_210_domesearch",
        "link": "37549946",
        "title_cate": "공연장",
        "human_review": "12",
        "blog_review": "1,925",
        "addresses": "서울 강서구 공항대로 376"
    }
]