[
    {
        "ranking": "1",
        "title": "부산별빛샌드 초량본점",
        "image_url": "https://search.pstatic.net/common?src=https%3A%2F%2Fldb-phinf.pstatic.net%2F20231130_131%2F17012714460150E9tU_JPEG%2FIMG_7537.jpeg&type=f210_210_domesearch",
        "link": "1168574749",
        "title_cate": "베이커리",
        "human_review": "43",
        "blog_review": "1,355",
        "addresses": "부산 동구 중앙대로308번길 4 1층 부산별빛샌드 초량본점",
        "x": "129.0448422",
        "y": "35.1236205"
    },
    {
        "ranking": "2",
        "title": "마루팥빙수단팥죽 본점",
        "image_url": "https://search.pstatic.net/common?src=https%3A%2F%2Fldb-phinf.pstatic.net%2F20171225_217%2F1514196430692PRTtB_JPEG%2FPaupEZnM3izxQuWL7QECFIzQ.jpg&type=f210_210_domesearch",
        "link": "32999091",
        "title_cate": "카페,디저트",
        "human_review": "2,146",
        "blog_review": "988",
        "addresses": "부산 동구 중앙대로179번길 9 1층 101호 마루팥빙수단팥죽 본점",
        "x": "129.0380627",
        "y": "35.1135595"
    },
    {
        "ranking": "3",
        "title": "아브니르",
        "image_url": "https://search.pstatic.net/common?src=https%3A%2F%2Fldb-phinf.pstatic.net%2F20240125_11%2F1706186219121YoSH2_JPEG%2FKakaoTalk_20240125_213030643_02.jpg&type=f210_210_domesearch",
        "link": "1664953620",
        "title_cate": "카페,디저트",
        "human_review": "1,738",
        "blog_review": "323",
        "addresses": "부산 동구 증산로 40 아브니르",
        "x": "129.0488087",
        "y": "35.1331542"
    },
    {
        "ranking": "4",
        "title": "부산과학체험관",
        "image_url": "https://search.pstatic.net/common?src=https%3A%2F%2Fldb-phinf.pstatic.net%2F20160415_254%2F1460698503484Om7f4_JPEG%2F176358518029099_0.jpeg&type=f210_210_domesearch",
        "link": "35794593",
        "title_cate": "과학관",
        "human_review": "813",
        "blog_review": "587",
        "addresses": "부산 동구 중앙대로260번길 11 부산과학체험관",
        "x": "129.0441329",
        "y": "35.1202723"
    },
    {
        "ranking": "5",
        "title": "브라운핸즈백제",
        "image_url": "https://search.pstatic.net/common?src=https%3A%2F%2Fldb-phinf.pstatic.net%2F20170511_276%2F1494464817295yoOf5_PNG%2F_1.png&type=f210_210_domesearch",
        "link": "37470097",
        "title_cate": "카페",
        "human_review": "3,666",
        "blog_review": "2,342",
        "addresses": "부산 동구 중앙대로209번길 16 1층",
        "x": "129.0391386",
        "y": "35.1163104"
    },
    {
        "ranking": "6",
        "title": "초량1941",
        "image_url": "https://search.pstatic.net/common?src=https%3A%2F%2Fldb-phinf.pstatic.net%2F20210308_6%2F1615177948541iwDs4_JPEG%2FdUwyAqOg8Byy9D-4Fh2i31Ax.jpeg.jpg&type=f210_210_domesearch",
        "link": "286366050",
        "title_cate": "카페,디저트",
        "human_review": "2,343",
        "blog_review": "2,382",
        "addresses": "부산 동구 망양로 533-5",
        "x": "129.0294333",
        "y": "35.119734"
    },
    {
        "ranking": "7",
        "title": "베이크백",
        "image_url": "https://search.pstatic.net/common?src=https%3A%2F%2Fldb-phinf.pstatic.net%2F20240323_11%2F1711182627309zEevp_JPEG%2F7652CD06-C543-450D-ABDE-37B93A514B2A.jpeg&type=f210_210_domesearch",
        "link": "1202551486",
        "title_cate": "카페,디저트",
        "human_review": "1,801",
        "blog_review": "485",
        "addresses": "부산 동구 초량중로 53 1층, 2층",
        "x": "129.038094",
        "y": "35.1168026"
    },
    {
        "ranking": "8",
        "title": "문화공감수정",
        "image_url": "https://search.pstatic.net/common?src=https%3A%2F%2Fldb-phinf.pstatic.net%2F20181119_14%2F154262053839870NDO_JPEG%2FZ1w9sl6qvrcUZXeQDIPn5oer.jpg&type=f210_210_domesearch",
        "link": "1138409494",
        "title_cate": "국가유산",
        "human_review": "95",
        "blog_review": "814",
        "addresses": "부산 동구 홍곡로 75",
        "x": "129.042727",
        "y": "35.1256686"
    },
    {
        "ranking": "9",
        "title": "동구 문화플랫폼",
        "image_url": "https://search.pstatic.net/common?src=https%3A%2F%2Fldb-phinf.pstatic.net%2F20220428_53%2F1651137898359bTFKw_JPEG%2F%25BD%25C3%25B9%25CE%25B8%25B6%25B4%25E7_%25BF%25DC%25BA%25CE.jpg&type=f210_210_domesearch",
        "link": "1582848344",
        "title_cate": "복합문화공간",
        "human_review": "8",
        "blog_review": "1,033",
        "addresses": "부산 동구 중앙대로 380",
        "x": "129.0496943",
        "y": "35.1288808"
    },
    {
        "ranking": "10",
        "title": "비엔씨 부산역점",
        "image_url": "https://search.pstatic.net/common?src=https%3A%2F%2Fldb-phinf.pstatic.net%2F20240408_49%2F1712533710172R6GxD_JPEG%2F1C3A2356.jpg&type=f210_210_domesearch",
        "link": "616538188",
        "title_cate": "베이커리",
        "human_review": "664",
        "blog_review": "573",
        "addresses": "부산 동구 중앙대로 206 2층 비엔씨",
        "x": "129.0417236",
        "y": "35.1153692"
    },
    {
        "ranking": "11",
        "title": "중앙공원",
        "image_url": "https://search.pstatic.net/common?src=https%3A%2F%2Fldb-phinf.pstatic.net%2F20150831_154%2F1441015969540uhLzu_JPEG%2F12391912_0.jpg&type=f210_210_domesearch",
        "link": "12391912",
        "title_cate": "도시,테마공원",
        "human_review": "11",
        "blog_review": "204",
        "addresses": "부산 동구 초량동 산63-5",
        "x": "129.0289716",
        "y": "35.1164249"
    },
    {
        "ranking": "12",
        "title": "초량온당",
        "image_url": "https://search.pstatic.net/common?src=https%3A%2F%2Fldb-phinf.pstatic.net%2F20220902_153%2F166204830512402Dx8_JPEG%2FKakaoTalk_20220902_010133007_02.jpg&type=f210_210_domesearch",
        "link": "1608109413",
        "title_cate": "베이커리",
        "human_review": "2,435",
        "blog_review": "1,166",
        "addresses": "부산 동구 초량중로 135 초량온당",
        "x": "129.0415503",
        "y": "35.1234295"
    },
    {
        "ranking": "13",
        "title": "갈매기샌드 부산본점",
        "image_url": "https://search.pstatic.net/common?src=https%3A%2F%2Fldb-phinf.pstatic.net%2F20230630_15%2F1688051959718q5qNF_JPEG%2FIMG_0264.jpeg&type=f210_210_domesearch",
        "link": "1192910224",
        "title_cate": "카페,디저트",
        "human_review": "448",
        "blog_review": "261",
        "addresses": "부산 동구 중앙대로226번길 7-2 1층 갈매기샌드",
        "x": "129.0420186",
        "y": "35.1168896"
    },
    {
        "ranking": "14",
        "title": "좌천동굴",
        "image_url": "https://search.pstatic.net/common?src=http%3A%2F%2Fblogfiles.naver.net%2FMjAyNDA2MDJfMTY2%2FMDAxNzE3MzA5OTc0MTEz.En4Fn7u65aTOFeZK3MQZgjQYDE2Ra_GfC6thVbQyZMwg.ZOeDycTT5nBjf3zzOBuJkgjB24ynu2mxWkSoG6sFR-og.JPEG%2FIMG_8201.jpg%23900x1200&type=f210_210_domesearch",
        "link": "1999348241",
        "title_cate": "동굴",
        "human_review": "7",
        "blog_review": "63",
        "addresses": "부산 동구 고관로185번길 13",
        "x": "129.0527313",
        "y": "35.1336311"
    },
    {
        "ranking": "15",
        "title": "카페편안",
        "image_url": "https://search.pstatic.net/common?src=https%3A%2F%2Fldb-phinf.pstatic.net%2F20211112_202%2F16367125021273s8mU_JPEG%2FIMG_20211024_121621_879.jpg&type=f210_210_domesearch",
        "link": "1507526064",
        "title_cate": "카페",
        "human_review": "635",
        "blog_review": "471",
        "addresses": "부산 동구 증산북로13번길 6",
        "x": "129.0518799",
        "y": "35.1387563"
    },
    {
        "ranking": "16",
        "title": "리센테",
        "image_url": "https://search.pstatic.net/common?src=https%3A%2F%2Fldb-phinf.pstatic.net%2F20230706_264%2F1688605664225XR5Ch_JPEG%2FIMG_5197.jpeg&type=f210_210_domesearch",
        "link": "1841632566",
        "title_cate": "카페",
        "human_review": "218",
        "blog_review": "219",
        "addresses": "부산 동구 충장대로 160 협성마리나G7 A동 3층 306호",
        "x": "129.0451184",
        "y": "35.1160847"
    },
    {
        "ranking": "17",
        "title": "카페 린 부산역점",
        "image_url": "https://search.pstatic.net/common?src=https%3A%2F%2Fldb-phinf.pstatic.net%2F20220712_64%2F1657592329802s0vYL_JPEG%2FIMG_3061.JPG&type=f210_210_domesearch",
        "link": "1575902921",
        "title_cate": "카페,디저트",
        "human_review": "1,559",
        "blog_review": "329",
        "addresses": "부산 동구 초량중로 103",
        "x": "129.0402226",
        "y": "35.120919"
    },
    {
        "ranking": "18",
        "title": "차이나타운",
        "image_url": "https://search.pstatic.net/common?src=http%3A%2F%2Fblogfiles.naver.net%2F20150222_216%2Fdorami7_1424608660395bSchx_JPEG%2FIMG_4875.JPG&type=f210_210_domesearch",
        "link": "35966224",
        "title_cate": "체험마을",
        "human_review": "75",
        "blog_review": "833",
        "addresses": "부산 동구 중앙대로179번길 1",
        "x": "129.0385301",
        "y": "35.1133998"
    },
    {
        "ranking": "19",
        "title": "부산항 힐링야영장",
        "image_url": "https://search.pstatic.net/common?src=https%3A%2F%2Fldb-phinf.pstatic.net%2F20180131_152%2F151739907860385iPI_JPEG%2F180120_%25BE%25DF%25BF%25B5%25C0%25E5%25281%2529.JPG&type=f210_210_domesearch",
        "link": "1256463037",
        "title_cate": "캠핑,야영장",
        "human_review": "",
        "blog_review": "421",
        "addresses": "부산 동구 초량동 1185-1",
        "x": "129.0503975",
        "y": "35.1117383"
    },
    {
        "ranking": "20",
        "title": "네살차이",
        "image_url": "https://search.pstatic.net/common?src=https%3A%2F%2Fldb-phinf.pstatic.net%2F20201025_201%2F1603629254230kBWKY_JPEG%2F4A2Baym6OhsMZuWMPn5mJSIL.jpeg.jpg&type=f210_210_domesearch",
        "link": "38463169",
        "title_cate": "카페",
        "human_review": "951",
        "blog_review": "1,694",
        "addresses": "부산 동구 중앙대로 447-1",
        "x": "129.0536999",
        "y": "35.1339956"
    }
]