[
    {
        "ranking": "1",
        "title": "대천해수욕장",
        "image_url": "https://search.pstatic.net/common?src=https%3A%2F%2Fldb-phinf.pstatic.net%2F20150901_295%2F1441038781982I4SWV_JPEG%2F157155537053107_0.jpg&type=f210_210_domesearch",
        "link": "https://map.naver.com/v5/entry/place/11784288"
    },
    {
        "ranking": "2",
        "title": "보령충청수영성",
        "image_url": "https://search.pstatic.net/common?src=http%3A%2F%2Fblogfiles.naver.net%2FMjAyNDA1MTlfMjEz%2FMDAxNzE2MDg0NDYwODg1.1eFEOzTB1gHJfAaE6D-ahVEI9sRMmEIXrebW8xB-Yvsg.WTr8Px23PS9ax1RDKFGoV9X7UzsAJwmOcvQuBbRctC8g.JPEG%2F%25BF%25A9%25C7%25E00522-%25C3%25E6%25C3%25BB%25BC%25F6%25BF%25B5%25BC%25BA.jpg%23600x600&type=f210_210_domesearch",
        "link": "https://map.naver.com/v5/entry/place/1838666037"
    },
    {
        "ranking": "3",
        "title": "죽도",
        "image_url": "https://search.pstatic.net/common?src=https%3A%2F%2Fldb-phinf.pstatic.net%2F20150831_248%2F1441008679931SziLy_JPEG%2F11629122_0.jpg&type=f210_210_domesearch",
        "link": "https://map.naver.com/v5/entry/place/11629122"
    },
    {
        "ranking": "4",
        "title": "성주산자연휴양림",
        "image_url": "https://search.pstatic.net/common?src=https%3A%2F%2Fldb-phinf.pstatic.net%2F20150831_185%2F1440992268718UOn3B_JPEG%2F11491440_0.jpg&type=f210_210_domesearch",
        "link": "https://map.naver.com/v5/entry/place/11491440"
    },
    {
        "ranking": "5",
        "title": "대천해수욕장 스카이바이크",
        "image_url": "https://search.pstatic.net/common?src=https%3A%2F%2Fldb-phinf.pstatic.net%2F20240421_87%2F1713664000456iSEd4_JPEG%2F%25C6%25F2%25C0%25CF%25B0%25FA_%25C1%25D6%25B8%25BB_%25BF%25EE%25C7%25E0%25BD%25C3%25B0%25A3%25C7%25A5_%25B1%25B8%25BA%25D0_%25281%2529001.jpg&type=f210_210_domesearch",
        "link": "https://map.naver.com/v5/entry/place/38328451"
    },
    {
        "ranking": "6",
        "title": "죽도 상화원",
        "image_url": "https://search.pstatic.net/common?src=https%3A%2F%2Fldb-phinf.pstatic.net%2F20181223_13%2F1545492597677arMX3_JPEG%2FjMqAo6NpI3pqeFaoQax1PuT0.jpg&type=f210_210_domesearch",
        "link": "https://map.naver.com/v5/entry/place/34325453"
    },
    {
        "ranking": "7",
        "title": "바이더오",
        "image_url": "https://search.pstatic.net/common?src=https%3A%2F%2Fldb-phinf.pstatic.net%2F20220124_141%2F1643007428525tywyE_JPEG%2FKakaoTalk_20220124_154108776_03.jpg&type=f210_210_domesearch",
        "link": "https://map.naver.com/v5/entry/place/1712146041"
    },
    {
        "ranking": "8",
        "title": "개화예술공원",
        "image_url": "https://search.pstatic.net/common?src=https%3A%2F%2Fldb-phinf.pstatic.net%2F20231006_190%2F1696604232506QLVg8_JPEG%2FIMG_7944.jpeg&type=f210_210_domesearch",
        "link": "https://map.naver.com/v5/entry/place/12024809"
    },
    {
        "ranking": "9",
        "title": "바다듬 루프탑카페",
        "image_url": "https://search.pstatic.net/common?src=https%3A%2F%2Fldb-phinf.pstatic.net%2F20220831_54%2F1661926173588xuRaP_JPEG%2F1.jpg&type=f210_210_domesearch",
        "link": "https://map.naver.com/v5/entry/place/1635643270"
    },
    {
        "ranking": "10",
        "title": "천북굴단지",
        "image_url": "https://search.pstatic.net/common?src=http%3A%2F%2Fblogfiles.naver.net%2FMjAyNDAxMjhfMTcy%2FMDAxNzA2NDQzODExMzQ5.-toEuhtMeirXVmuWKH2uu9pA28uBLIHGG1rm9EvIdhMg.50frYLE1Prz8PUg4Tp0XKCy-bBomMXFp0W0_3UcoYYgg.JPEG.cseyo%2FIMG_3660.JPG%234032x3024&type=f210_210_domesearch",
        "link": "https://map.naver.com/v5/entry/place/17715970"
    },
    {
        "ranking": "11",
        "title": "보령석탄박물관",
        "image_url": "https://search.pstatic.net/common?src=https%3A%2F%2Fldb-phinf.pstatic.net%2F20210725_8%2F16271987424954CX7I_JPEG%2FeHdFzHW2urHzFpGp8SWsXQCI.jpg&type=f210_210_domesearch",
        "link": "https://map.naver.com/v5/entry/place/11620648"
    },
    {
        "ranking": "12",
        "title": "용두해수욕장",
        "image_url": "https://search.pstatic.net/common?src=https%3A%2F%2Fldb-phinf.pstatic.net%2F20150831_245%2F1440992297729jAMTb_JPEG%2F157155537051800_0.jpg&type=f210_210_domesearch",
        "link": "https://map.naver.com/v5/entry/place/11491760"
    },
    {
        "ranking": "13",
        "title": "오서산자연휴양림",
        "image_url": "https://search.pstatic.net/common?src=https%3A%2F%2Fldb-phinf.pstatic.net%2F20150831_133%2F14409922178567O3WQ_JPEG%2F11491038_0.jpg&type=f210_210_domesearch",
        "link": "https://map.naver.com/v5/entry/place/11491038"
    },
    {
        "ranking": "14",
        "title": "코랄커피",
        "image_url": "https://search.pstatic.net/common?src=https%3A%2F%2Fldb-phinf.pstatic.net%2F20200429_39%2F158816515347548J1g_PNG%2FFQPIRs9-dcM64vJVGxjKw-7q.png&type=f210_210_domesearch",
        "link": "https://map.naver.com/v5/entry/place/21535890"
    },
    {
        "ranking": "15",
        "title": "갱스커피",
        "image_url": "https://search.pstatic.net/common?src=https%3A%2F%2Fldb-phinf.pstatic.net%2F20221209_101%2F1670574167200rCss5_JPEG%2FB3DEE179-4239-4D45-AF70-5D01B54E21E6.jpeg&type=f210_210_domesearch",
        "link": "https://map.naver.com/v5/entry/place/1147211842"
    },
    {
        "ranking": "16",
        "title": "우유창고",
        "image_url": "https://search.pstatic.net/common?src=https%3A%2F%2Fldb-phinf.pstatic.net%2F20230614_181%2F16867157043972YhK0_PNG%2FKakaoTalk_20230614_130730438_02.png&type=f210_210_domesearch",
        "link": "https://map.naver.com/v5/entry/place/479989353"
    },
    {
        "ranking": "17",
        "title": "바둑이네동물원",
        "image_url": "https://search.pstatic.net/common?src=https%3A%2F%2Fldb-phinf.pstatic.net%2F20240308_266%2F1709869142697leMKe_JPEG%2F2024%25BF%25E4%25B1%25DD%25BE%25C8%25B3%25BB2.jpg&type=f210_210_domesearch",
        "link": "https://map.naver.com/v5/entry/place/34850135"
    },
    {
        "ranking": "18",
        "title": "효자도",
        "image_url": "https://search.pstatic.net/common?src=http%3A%2F%2Fblogfiles.naver.net%2F20140713_80%2Fktl_14052303562672uPHu_JPEG%2F%25C5%25A9%25B1%25E2%25BA%25AF%25C8%25AF_%25C8%25BF%25C0%25DA%25B5%25B514.JPG%23924x622&type=f210_210_domesearch",
        "link": "https://map.naver.com/v5/entry/place/13491830"
    },
    {
        "ranking": "19",
        "title": "머드광장",
        "image_url": "https://search.pstatic.net/common?src=http%3A%2F%2Fblogfiles.naver.net%2FMjAyNDAxMjVfODMg%2FMDAxNzA2MTY1Mzg0NzY4.yl-_kQEW4k2YZKalxcTUaWISWXHJtjWG2NvlcUCoNKIg.9GTzMHTt3Q-a38dDCLRdMgkuBzVQ5JrXlghD5XgfwiIg.JPEG.sweetten%2F20240121%25A3%25DF110943.jpg%23900x675&type=f210_210_domesearch",
        "link": "https://map.naver.com/v5/entry/place/1142570640"
    },
    {
        "ranking": "20",
        "title": "군헌갯벌체험학습장",
        "image_url": "https://search.pstatic.net/common?src=http%3A%2F%2Fblogfiles.naver.net%2FMjAyMzA5MTFfMjcg%2FMDAxNjk0MzYxODU0NTU5.yVV41ipZ9_hFHfM0nmhOxcUvvs2_DKFM5BLAeNtp0Lwg.abefsgBQjrWwT2CMPPlT7slxfjHdwDAISZGwsHkCCY8g.JPEG.toymusic7942%2FKakaoTalk_20230911_010005464_09.jpg%234032x3024&type=f210_210_domesearch",
        "link": "https://map.naver.com/v5/entry/place/17712637"
    }
]