[
    {
        "ranking": "1",
        "title": "P.E.I coffee",
        "image_url": "https://search.pstatic.net/common?src=https%3A%2F%2Fldb-phinf.pstatic.net%2F20220905_60%2F1662304060905UggdB_JPEG%2FKakaoTalk_20220905_000613409_06.jpg&type=f210_210_domesearch",
        "link": "https://map.naver.com/v5/entry/place/1715012643"
    },
    {
        "ranking": "2",
        "title": "휴휴암",
        "image_url": "https://search.pstatic.net/common?src=https%3A%2F%2Fldb-phinf.pstatic.net%2F20220321_79%2F1647854503013cOJLN_JPEG%2F20220321_100422.jpg&type=f210_210_domesearch",
        "link": "https://map.naver.com/v5/entry/place/13502101"
    },
    {
        "ranking": "3",
        "title": "킨십",
        "image_url": "https://search.pstatic.net/common?src=https%3A%2F%2Fldb-phinf.pstatic.net%2F20231206_11%2F1701866823094n1c7x_JPEG%2FIMG_6867.jpeg&type=f210_210_domesearch",
        "link": "https://map.naver.com/v5/entry/place/1107656137"
    },
    {
        "ranking": "4",
        "title": "바다뷰제빵소",
        "image_url": "https://search.pstatic.net/common?src=https%3A%2F%2Fldb-phinf.pstatic.net%2F20230112_300%2F1673517969118qt8PN_JPEG%2FKakaoTalk_20221117_211350985_13.jpg&type=f210_210_domesearch",
        "link": "https://map.naver.com/v5/entry/place/1238869844"
    },
    {
        "ranking": "5",
        "title": "쏠비치 양양 오션플레이",
        "image_url": "https://search.pstatic.net/common?src=https%3A%2F%2Fldb-phinf.pstatic.net%2F20201215_276%2F1608018654825dK4Nq_JPEG%2F%25BE%25E7%25BE%25E7.jpg&type=f210_210_domesearch",
        "link": "https://map.naver.com/v5/entry/place/13474425"
    },
    {
        "ranking": "6",
        "title": "낙산사 템플스테이",
        "image_url": "https://search.pstatic.net/common?src=https%3A%2F%2Fldb-phinf.pstatic.net%2F20240221_162%2F1708502147700KHOIR_JPEG%2FKakaoTalk_20240113_131758292.jpg&type=f210_210_domesearch",
        "link": "https://map.naver.com/v5/entry/place/38643729"
    },
    {
        "ranking": "7",
        "title": "물치해수욕장",
        "image_url": "https://search.pstatic.net/common?src=https%3A%2F%2Fldb-phinf.pstatic.net%2F20150901_295%2F1441045712737wkrbd_JPEG%2F157155537036565_0.jpg&type=f210_210_domesearch",
        "link": "https://map.naver.com/v5/entry/place/13491983"
    },
    {
        "ranking": "8",
        "title": "플리즈웨잇",
        "image_url": "https://search.pstatic.net/common?src=https%3A%2F%2Fldb-phinf.pstatic.net%2F20220317_205%2F1647492351069pRraO_JPEG%2FP20220312_153053395_6AF5FCC7-B747-4007-AB0A-4D0DAD0F92C8.JPG&type=f210_210_domesearch",
        "link": "https://map.naver.com/v5/entry/place/1174155263"
    },
    {
        "ranking": "9",
        "title": "카페 로그",
        "image_url": "https://search.pstatic.net/common?src=https%3A%2F%2Fldb-phinf.pstatic.net%2F20240322_6%2F1711084662497yeuud_JPEG%2FKakaoTalk_20240322_135336793.jpg&type=f210_210_domesearch",
        "link": "https://map.naver.com/v5/entry/place/1358535239"
    },
    {
        "ranking": "10",
        "title": "오산리선사유적박물관",
        "image_url": "https://search.pstatic.net/common?src=https%3A%2F%2Fldb-phinf.pstatic.net%2F20181002_238%2F1538475899444jgucO_JPEG%2FvLGxmzQ5B5YD7WicoEajmYSX.jpg&type=f210_210_domesearch",
        "link": "https://map.naver.com/v5/entry/place/12413701"
    },
    {
        "ranking": "11",
        "title": "페이보릿",
        "image_url": "https://search.pstatic.net/common?src=https%3A%2F%2Fldb-phinf.pstatic.net%2F20220502_249%2F1651465263911pkgDD_JPEG%2F8F089375-52BB-4C5F-8780-BD60E8BAD878.jpeg&type=f210_210_domesearch",
        "link": "https://map.naver.com/v5/entry/place/1222493418"
    },
    {
        "ranking": "12",
        "title": "Farm11",
        "image_url": "https://search.pstatic.net/common?src=https%3A%2F%2Fldb-phinf.pstatic.net%2F20191124_292%2F1574558133564OaUng_JPEG%2F29CM6893.jpg&type=f210_210_domesearch",
        "link": "https://map.naver.com/v5/entry/place/1637889240"
    },
    {
        "ranking": "13",
        "title": "드리프터 양양",
        "image_url": "https://search.pstatic.net/common?src=https%3A%2F%2Fldb-phinf.pstatic.net%2F20240410_4%2F1712675799826gEoMr_JPEG%2F%25B5%25E5%25B8%25AE%25C7%25C1%25C5%25CD%25B1%25A4%25B0%25ED-01.jpg&type=f210_210_domesearch",
        "link": "https://map.naver.com/v5/entry/place/1335584931"
    },
    {
        "ranking": "14",
        "title": "하조대해수욕장",
        "image_url": "https://search.pstatic.net/common?src=https%3A%2F%2Fldb-phinf.pstatic.net%2F20150901_9%2F1441045658234BnirT_JPEG%2F157155537037786_0.jpg&type=f210_210_domesearch",
        "link": "https://map.naver.com/v5/entry/place/13491656"
    },
    {
        "ranking": "15",
        "title": "낙산사",
        "image_url": "https://search.pstatic.net/common?src=https%3A%2F%2Fldb-phinf.pstatic.net%2F20240225_126%2F1708836820246VhsFP_PNG%2F001.png&type=f210_210_domesearch",
        "link": "https://map.naver.com/v5/entry/place/12991231"
    },
    {
        "ranking": "16",
        "title": "엉클서프 양양",
        "image_url": "https://search.pstatic.net/common?src=https%3A%2F%2Fldb-phinf.pstatic.net%2F20230803_251%2F1691052595750a6kkN_JPEG%2F1691052498041.jpg&type=f210_210_domesearch",
        "link": "https://map.naver.com/v5/entry/place/1113484449"
    },
    {
        "ranking": "17",
        "title": "주전골계곡",
        "image_url": "https://search.pstatic.net/common?src=https%3A%2F%2Fldb-phinf.pstatic.net%2F20150831_139%2F14410144904031Vsrq_JPEG%2F12152644_0.jpg&type=f210_210_domesearch",
        "link": "https://map.naver.com/v5/entry/place/12152644"
    },
    {
        "ranking": "18",
        "title": "예쁘다 하조대",
        "image_url": "https://search.pstatic.net/common?src=https%3A%2F%2Fldb-phinf.pstatic.net%2F20190402_129%2F1554196279215xlAnd_JPEG%2FmgXsG0vRYYlyzr93tCMZxrBM.jpg&type=f210_210_domesearch",
        "link": "https://map.naver.com/v5/entry/place/1930202461"
    },
    {
        "ranking": "19",
        "title": "하조대전망대",
        "image_url": "https://search.pstatic.net/common?src=http%3A%2F%2Fblogfiles.naver.net%2FMjAxODAyMjZfODMg%2FMDAxNTE5NjQ4MzIwMjg2.SKUV4PWAmXGTdn-RSX8nddaHyXfNNNguucLOKaeB6Ekg.o9jQLoPUHaenvbpArhUvUuJ-hWTT3R5Xe8JgQXsoolUg.JPEG.ps_yarn%2FIMG_0741.JPG%23740x493&type=f210_210_domesearch",
        "link": "https://map.naver.com/v5/entry/place/1890774351"
    },
    {
        "ranking": "20",
        "title": "정암해수욕장",
        "image_url": "https://search.pstatic.net/common?src=https%3A%2F%2Fldb-phinf.pstatic.net%2F20150901_129%2F1441045540131wGsnx_JPEG%2F157155537036222_0.jpg&type=f210_210_domesearch",
        "link": "https://map.naver.com/v5/entry/place/13490895"
    }
]